Workbook

Sheet 01_AUTODIAGNOSTIC
A1: ID | B1: Question DCSSI | C1: Note 0–3 | D1: Références P/T | E1: Justification factuelle | F1: Confiance
A2: Q01 | B2: Adhérence du SI aux missions | C2: 3 | D2: P01, P03, P04 | E2: MEDICA-SERVICES vend l'hébergement et l'exploitation d'applications pour 12 établissements de soins (P01). Sans SI il n'existe plus de prestation et les clients reviennent au papier (P04). Le SI est vital aux missions. | F2: Confirmé
A3: Q02 | B3: Impacts internes | C3: 2 | D3: P01, P04 | E3: La DG prévoit de fortes pertes contractuelles après une journée d'arrêt et le départ de certains clients si l'arrêt se prolonge (P04). Elle estime pouvoir poursuivre des prestations manuelles, ce qui écarte une conséquence fatale démontrée. | F3: Probable
A4: Q03 | B4: Impacts externes | C4: 3 | D4: P04, P05 | E4: Les établissements clients basculent sur papier (P04) et une altération non détectée peut provoquer des erreurs d'orientation et de prise en charge de patients (P05). La sécurité de personnes chez des tiers est en jeu. Note fondée sur des déclarations, sans étude d'impact chiffrée. | F4: Probable
A5: Q04 | B5: Disponibilité | C5: 2 | D5: P01, P04, P05 | E5: Une journée d'arrêt du portail est grave (pertes contractuelles, P04) et un arrêt prolongé affecte fortement la continuité des soins (P05). La DG décrit une activité dégradée et non un arrêt définitif, d'où 2 et non 3. Reprise contractuelle sous 8 h (P01). | F5: Probable
A6: Q05 | B6: Intégrité | C6: 2 | D6: P05 | E6: Les environnements contiennent des identifiants patients et des informations de santé. Une altération non détectée peut provoquer des erreurs d'orientation et de prise en charge (P05). L'impact est grave pour l'activité. Aucune pièce ne le décrit comme fatal pour l'entreprise, d'où 2 par cohérence avec Q02 et Q04. | F6: Probable
A7: Q06 | B7: Confidentialité | C7: 3 | D7: P05, P07 | E7: Identifiants patients et données de santé (P05). La DSI qualifie la divulgation de risque critique et les attaquants visés cherchent la revente de données et l'extorsion (P07). | F7: Probable
A8: Q07 | B8: Fréquence des sinistres | C8: 2 | D8: P06 | E8: Dix événements SSI enregistrés en 12 mois, soit environ 2,5 par trimestre (P06). Le registre n'étant ni exhaustif ni revu, la fréquence réelle peut être supérieure. | F8: Probable
A9: Q08 | B9: Motivation des attaquants | C9: 2 | D9: P07 | E9: Menaces ciblées jugées plausibles et potentiellement fortement motivées par la revente de données et l'extorsion (P07). Aucune pièce ne justifie le niveau très important. | F9: Probable
A10: Q09 | B10: Moyens des attaquants | C10: 2 | D10: P07 | E10: P07 écarte les moyens illimités. Une cybercriminalité d'extorsion dispose plausiblement de moyens importants. Hypothèse d'auditeur sans effet sur le maximum du groupe, déjà fixé à 2 par Q07 et Q08. | F10: Incertain
A11: Q10 | B11: Hétérogénéité du SI | C11: 2 | D11: P08, T01 | E11: Windows, Linux, hyperviseurs, réseau multi-constructeurs, SaaS et application propriétaire héritée. P08 qualifie l'architecture de fortement hétérogène mais non extrêmement hétérogène. | F11: Confirmé
A12: Q11 | B12: Ouverture du SI | C12: 2 | D12: P03, P07, T01, T02 | E12: Interconnexions clients encadrées par contrat (P07). Le portail est ouvert à des internautes non maîtrisés, mais par une publication unique filtrée (FW-01, FW-08) et un reverse proxy en DMZ (P03, T01, T02). Ouverture externe jugée sous contrôle. La note 3 serait défendable si l'on considère que l'accès public au portail échappe au contrôle de l'organisme. La somme passerait alors à 11 et la cible à 5. | F12: Probable
A13: Q12 | B13: Variabilité du SI | C13: 2 | D13: P06, P08 | E13: Changements applicatifs mensuels et d'infrastructure trimestriels (P08), deux indisponibilités dues à des changements (P06). Le SI change relativement souvent. | F13: Confirmé
A16: Conséquences (Q01–03) | B16: =IF(COUNT(C2:C4)<3,"",MAX(C2:C4)) -> 3
A17: Sensibilité (Q04–06) | B17: =IF(COUNT(C5:C7)<3,"",MAX(C5:C7)) -> 3
A18: Menaces (Q07–09) | B18: =IF(COUNT(C8:C10)<3,"",MAX(C8:C10)) -> 2
A19: Vulnérabilités (Q10–12) | B19: =IF(COUNT(C11:C13)<3,"",MAX(C11:C13)) -> 2
A20: Somme des 4 maxima | B20: =IF(COUNT(B16:B19)<4,"",SUM(B16:B19)) -> 10
A21: Niveau adéquat calculé | B21: =IF(B20="","",IF(B20<=2,1,IF(B20<=5,2,IF(B20<=8,3,IF(B20<=10,4,5))))) -> 4
A22: Ajustement justifié (−1/0/+1) | B22: 0
A23: Cible proposée | B23: =IF(B21="","",MAX(1,MIN(5,B21+B22))) -> 4

Sheet 02_MATURITE_EFFECTIVE
A1: Processus DCSSI | B1: Niveau revendiqué | C1: Niveau effectif 0–5 | D1: Preuves P/T | E1: Exigences manquantes / réserve | F1: Écart cible–effectif | G1: Action de progression
A2: Définir la stratégie SSI | B2: Non déclaré | C2: 1 | D2: P09, P02, P17 | E2: Niveau 1 étayé par la note d'orientation 2024 approuvée par la DG, des priorités annuelles et un référent (P09). Niveau 2 indéterminé car aucune mesure qualitative n'est documentée et le compte rendu semestriel reste oral, sans trace écrite fournie. Niveau 3 non atteint, faute de processus commun documenté (P09). Revue annuelle de la PSSI sans PV depuis deux ans (P17). | F2: =IF(OR(C2="",'01_AUTODIAGNOSTIC'!B23=""),"",MAX(0,'01_AUTODIAGNOSTIC'!B23-C2)) -> 3 | G2: Tableau de bord qualitatif semestriel et comptes rendus écrits validés par la DG, intégrés au lot A01 (pilote RSSI). Preuve : deux PV de revue datés.
A3: Gérer les risques SSI | B3: Non déclaré | C3: 1 | D3: P10, P06 | E3: Risques recensés ponctuellement lors de projets récents, avec des mesures décidées (P10). Niveau 2 non atteint : ni calendrier de revue, ni méthode réutilisable, ni registre consolidé approuvé. L'analyse du prestataire de 2025 reste isolée. | F3: =IF(OR(C3="",'01_AUTODIAGNOSTIC'!B23=""),"",MAX(0,'01_AUTODIAGNOSTIC'!B23-C3)) -> 3 | G3: Méthode simple, registre consolidé et revue trimestrielle (A01). Preuve : registre approuvé par la DG et PV de revue.
A4: Gérer les règles SSI | B4: Non déclaré | C4: 2 | D4: P11, P17, T06 | E4: Niveau 2 étayé par une PSSI approuvée, des règles écrites, une application planifiée, des contrôles qualitatifs consignés et l'information des managers (P11). Niveau 3 non atteint, les textes ne forment pas un processus commun. Fragilités : revue annuelle sans PV (P17) et aucune cible de délai de correctifs (T06). | F4: =IF(OR(C4="",'01_AUTODIAGNOSTIC'!B23=""),"",MAX(0,'01_AUTODIAGNOSTIC'!B23-C4)) -> 2 | G4: PSSI révisée avec délais de correctifs par criticité, diffusée à tout le périmètre (A03). Preuve : PSSI v2 approuvée, PV de revue, taux de sensibilisation.
A5: Superviser la SSI | B5: Non déclaré | C5: 1 | D5: P12, P06, T08 | E5: Outil de journalisation et alertes actifs, interventions à la demande (P12), d'où le niveau 1. Niveau 2 non atteint : aucune campagne de contrôle planifiée, aucun reporting régulier ni procédure commune (P12). AL-1048 fermée automatiquement sans ticket (T08). | F5: =IF(OR(C5="",'01_AUTODIAGNOSTIC'!B23=""),"",MAX(0,'01_AUTODIAGNOSTIC'!B23-C5)) -> 3 | G5: Plan de contrôle annuel, procédure de traitement des alertes et reporting mensuel (A02). Preuve : échantillon de tickets d'alerte qualifiés et rapports mensuels.
A6: Concevoir les mesures SSI | B6: Non déclaré | C6: 2 | D6: P13, T02 | E6: Besoins identifiés sur certains projets, fiche type, responsable technique désigné, revues planifiées pour les projets majeurs avec compte rendu écrit remonté au responsable (P13). Le compte rendu écrit des revues est retenu comme mesure qualitative. La compétence est retenue, comme pour les autres processus, sur la base d'un rôle désigné chargé de la sécurité, à confirmer en entretien. Niveau 3 non atteint, la démarche n'est pas globale. La règle provisoire FW-17 (T02) l'illustre sans le prouver. | F6: =IF(OR(C6="",'01_AUTODIAGNOSTIC'!B23=""),"",MAX(0,'01_AUTODIAGNOSTIC'!B23-C6)) -> 2 | G6: Fiche de besoins SSI obligatoire pour tout projet ou changement significatif (préparée en régie, A04 différée). Preuve : fiches sur un échantillon de projets.
A7: Réaliser les mesures SSI | B7: Non déclaré | C7: 1 | D7: P14, T02 | E7: Niveau 1 étayé par des déploiements préparés par des techniciens compétents (P14). Comptes rendus d'installation et de validation, suivi régulier et information de la DSI couvrent quatre exigences du niveau 2. Niveau 2 indéterminé car la planification n'est pas démontrée, P14 indiquant seulement que les déploiements sont « souvent préparés ». Règles FW-17 et FW-31 sans justification ni validation (T02). | F7: =IF(OR(C7="",'01_AUTODIAGNOSTIC'!B23=""),"",MAX(0,'01_AUTODIAGNOSTIC'!B23-C7)) -> 3 | G7: Plan de déploiement trimestriel des mesures et modèle commun de recette, en régie (pilote DSI). Preuve : plans datés et PV de recette sur trois déploiements.
A8: Exploiter les mesures SSI | B8: Non déclaré | C8: 2 | D8: P15, P17, T03, T04, T06, T09 | E8: Sauvegardes planifiées, comptes rendus hebdomadaires, astreinte, procédure de restauration connue et bilan qualitatif mensuel à la DSI (P15). Niveau 3 non atteint. Fragilités : 2 PV de test sur 9 services (T09), MFA sur 6 comptes privilégiés sur 10 (T04), correctifs en retard sans exception (T06), déclarations de la DG non démontrées et de la DSI contredites (P17). | F8: =IF(OR(C8="",'01_AUTODIAGNOSTIC'!B23=""),"",MAX(0,'01_AUTODIAGNOSTIC'!B23-C8)) -> 2 | G8: Standardiser restauration, correctifs et revue des comptes (A05, A08, A09). Preuve : PV de restauration avec RTO et RPO mesurés, export MFA, SLA de correctifs.

Sheet 03_CONSTATS_TECHNIQUES
A1: ID | B1: Pièces | C1: Observation / fait | D1: Qualification / réserve | E1: Processus associé | F1: Scénario de risque | G1: Priorité justifiée | H1: Recommandation et pilote | I1: Preuve de clôture
A2: C01 | B2: T03/T04 | C2: 10 comptes privilégiés recensés, 6 enrôlés MFA (60 %). Sans MFA : svc-backup, admin-old (Domain Admin, dernière activité documentée 2025-02-14), admin-presta (VPN prestataire) et admin-db. | D2: Fait documenté sur le périmètre de l'export (annuaire et administrateurs VPN). Exhaustivité SaaS non garantie, accès conditionnel et exceptions non fournis. Contredit la déclaration de la DSI (P17). | E2: Exploiter les mesures SSI | F2: Prise de contrôle d'un compte privilégié sans second facteur puis modification non autorisée de l'AD (R01). | G2: Élevée : privilèges étendus, accès VPN exposé, signaux T07 sur admin-old. | H2: DSI (IAM) : désactiver ou justifier admin-old, MFA pour admin-presta et admin-db, restriction de svc-backup (A08). | I2: Export MFA exhaustif à 100 % ou exceptions approuvées, preuve de restriction de svc-backup, revue des groupes à privilèges.
A3: C02 | B3: T02/T01 | C3: La règle FW-31 autorise tout service du VLAN 40 (postes) vers le VLAN 60 (BACKUP01). Règle héritée sans justification. | D3: Configuration extraite sans journaux de trafic. Usage réel inconnu. Aucune exploitation constatée. | E3: Concevoir / Réaliser les mesures SSI | F3: Un poste compromis par hameçonnage atteint BACKUP01 et chiffre ou supprime les copies, ce qui empêche la reprise (R02). | G3: Élevée : les sauvegardes sont le dernier recours de reprise et l'hameçonnage est fréquent (P06). | H3: DSI réseau : restreindre FW-31 aux flux nécessaires après analyse des journaux, en régie sous un mois. | I3: Règle supprimée ou justifiée et approuvée, journaux de trafic sur 30 jours, test de segmentation.
A4: C03 | B4: T05/T06 | C4: APP01 (criticité métier critique) sans correctif critique éditeur (CVSS communiqué 9,8, T05). L'hôte affiche 74 jours de retard de correctifs au 12/10/2026, exception non documentée (T06). | D4: Non exposé directement à Internet et non exploité pendant l'audit. Date de publication du correctif critique, CVE, version et historique de déploiement absents. Retard déclaratif. | E4: Exploiter les mesures SSI | F4: Rebond depuis WEB01 (flux WEB01 vers APP01) ou via RDP (FW-17) puis exploitation d'APP01, altération ou fuite de données patients (R03). | G4: Élevée : actif critique joignable depuis la DMZ, aucune exception validée. Le score seul ne fixe pas la priorité. | H4: Responsable infrastructures : correctif sous 15 jours ou exception signée avec mesures compensatoires, traité en tête du lot A09. | I4: Scan authentifié après correctif, ticket de changement, version installée.
A5: C04 | B5: T07/T08 | C5: Le 09/10/2026, trois échecs puis un succès VPN pour admin-old depuis 198.51.100.44 (00:13), ajout au groupe Server-Admins (00:18), alerte AL-1048 de sévérité HIGH (00:22) fermée automatiquement après 24 h sans ticket. | D5: Signaux compatibles avec un événement à investiguer, pas une compromission prouvée. Intégrité des journaux, trace MFA et contact du titulaire non fournis. Incohérence avec la dernière activité T03 (2025-02-14). | E5: Superviser la SSI | F5: Usage frauduleux non détecté d'un compte à privilèges et persistance de droits (R01). | G5: Très élevée : privilège Domain Admin, compte sans MFA, aucun examen de l'alerte tracé. | H5: RSSI : ouvrir un incident, mesures conservatoires (désactivation d'admin-old, revue de Server-Admins, préservation des journaux), investigation, fin de la fermeture automatique des alertes HIGH (A02). | I5: Ticket d'incident qualifié, rapport d'investigation, membres de Server-Admins avant et après, paramétrage SIEM modifié.
A6: C05 | B6: T09 | C6: 9 services dans le périmètre, 2 PV de test (MEDI-PORTAL le 15/09, ticketing le 16/09/2026), 7 sans PV. RPO non fourni. Sauvegarde M365 alléguée chez un tiers. | D6: L'absence de PV ne prouve pas l'absence de test. Le contenu des deux PV n'est pas communiqué, le respect du RTO de 8 h n'est donc pas démontré (P01, T09). Déclaration de la DG non démontrée (P17). | E6: Exploiter les mesures SSI | F6: Restauration impossible ou trop lente après rançongiciel, dépassement du RTO contractuel (R02). | G6: Élevée : engagement contractuel et continuité des soins (P01, P05). | H6: Responsable infrastructures : plan de tests trimestriel couvrant les 9 services (A05). | I6: PV de restauration datés avec durée mesurée et RPO constaté pour chaque service.
A7: C06 | B7: T02/T01 | C7: FW-17 autorise RDP (3389/TCP) depuis VPN-ADMIN vers tout le VLAN 20, sans passer par BASTION01. Règle déclarée provisoire. | D7: Durée, utilisateurs et journaux non fournis. Le contournement du bastion est déduit du schéma T01. | E7: Réaliser les mesures SSI | F7: Un compte VPN sans MFA (admin-presta) atteint APP01 ou DB01 en RDP sans traçabilité du bastion (R01, R03). | G7: Élevée : accès d'administration direct vers les serveurs critiques. | H7: DSI : retirer FW-17 ou lui fixer une date d'expiration, imposer le passage par le bastion. | I7: Règle supprimée, connexions RDP tracées sur BASTION01.
A8: C07 | B8: T02/T05/T06 | C8: FW-19 ouvre SMB (445/TCP) de tout le VLAN 40 vers le VLAN 30. Signature SMB non obligatoire sur SRV-FICHIERS (CVSS 6,5). Correctifs en retard de 43 jours. | D8: Constat de scanner non validé manuellement. Périmètre « large » sans liste des partages. | E8: Concevoir les mesures SSI | F8: Relais d'authentification ou propagation latérale depuis un poste compromis, divulgation de données (R04). | G8: Moyenne à élevée : exposition interne étendue et hameçonnage fréquent. | H8: Responsable infrastructures : signature SMB obligatoire, restriction de FW-19 aux groupes métiers (A09). | I8: Stratégie de groupe appliquée, scan de contrôle, matrice des partages.
A9: C08 | B9: T02/T05 | C9: Depuis le point de mesure DMZ, WEB01 répond sur 80/tcp et 443/tcp, 22/tcp filtré. Le scanner signale TLS 1.0 (CVSS 5,3). La redirection HTTP vers HTTPS est déclarée, non vérifiée. | D9: Scan non authentifié depuis la DMZ, aucune vue depuis Internet. Validation manuelle absente. Un port ouvert ne prouve pas une faille exploitée. | E9: Exploiter les mesures SSI | F9: Dégradation du chiffrement des sessions du portail public (R05). | G9: Modérée : exposé à Internet mais impact limité si la redirection est effective. | H9: Responsable infrastructures : désactiver TLS 1.0 et 1.1, vérifier la redirection et activer HSTS, scan externe de contrôle (A09). | I9: Rapport de test TLS et preuve de redirection permanente.
A10: C09 | B10: T06/P11/T05 | C10: La PSSI ne fixe aucun délai de correctifs par criticité. Retards de 12 j (WEB01), 43 j (SRV-FICHIERS) et 74 j (APP01) sans exception validée. AD01 à jour selon l'agent (inventaire du 25/09/2026). | D10: Retards déclaratifs, historiques de déploiement absents. Inventaire AD01 ancien de 17 jours à la date de contrôle. | E10: Gérer les règles SSI | F10: Fenêtre d'exposition prolongée sur des actifs critiques (R03). | G10: Élevée : cause commune de C03, C07 et C08. | H10: RSSI : SLA par criticité et circuit d'exception (A03, A09). | I10: SLA approuvés, tableau mensuel de conformité, exceptions signées.
A11: C10 | B11: P06/P12/T08 | C11: Registre de 10 événements non exhaustif et non revu en comité (P06). Alertes parfois conservées dans les tickets (P12), AL-1048 sans ticket (T08). | D11: Pièces de gouvernance déclaratives, cohérentes avec T08. | E11: Superviser la SSI | F11: Incidents non qualifiés et absence de retour d'expérience (R01). | G11: Élevée : conditionne la détection. | H11: RSSI : registre unique alimenté par les alertes qualifiées et revue mensuelle (A02). | I11: Registre consolidé, PV de revue, taux d'alertes HIGH qualifiées.
A12: C11 | B12: T03/T09 | C12: svc-backup, compte technique à droits élevés sans MFA, déclaré non interactif par la DSI sans preuve de restriction. | D12: Déclaration non étayée. Lien avec BACKUP01 probable mais non documenté. | E12: Exploiter les mesures SSI | F12: Détournement du compte de sauvegarde pour supprimer les copies (R02). | G12: Élevée : touche la capacité de reprise. | H12: DSI (IAM) : interdire l'ouverture de session interactive, secret en coffre, rotation (A08). | I12: Stratégie de refus d'ouverture de session appliquée, journal sans session interactive.
A13: C12
A14: C13
A15: C14
A16: C15

Sheet 04_REGISTRE_RISQUES
A1: ID | B1: Événement redouté | C1: Actif | D1: Menace / source | E1: Vulnérabilité ou faiblesse | F1: Mesures existantes | G1: Impact 1–4 | H1: Vraisemblance 1–4 | I1: Score I×V | J1: Décision / traitement | K1: Preuves
A2: R01 | B2: Prise de contrôle d'un compte à privilèges menant à une modification non autorisée de l'infrastructure (AD, serveurs) | C2: AD01, BASTION01 et VPN, groupe Server-Admins | D2: Attaquant externe à motivation cupide (P07) ou abus d'un accès prestataire | E2: 4 comptes privilégiés sur 10 non enrôlés MFA dont admin-old (dernière activité documentée en 2025, T03) et admin-presta, RDP direct FW-17, AL-1048 fermée sans examen tracé | F2: MFA enrôlé sur 6 comptes sur 10, SIEM avec alertes, bastion pour une partie des accès | G2: 4 | H2: 3 | I2: =IF(OR(G2="",H2=""),"",G2*H2) -> 12 | J2: Réduire (A08, A02) et mesures conservatoires immédiates. Décision DG sur proposition du RSSI. | K2: T03, T04, T07, T08, P17 · C01, C04, C06, C10
A3: R02 | B3: Indisponibilité de MEDI-PORTAL au-delà du RTO de 8 h faute de restauration fiable (rançongiciel ou panne) | C3: MEDI-PORTAL, base de données MEDI, BACKUP01 | D3: Rançongiciel après hameçonnage ou erreur d'exploitation | E3: 2 tests documentés sur 9 services, RPO inconnu, FW-31 Any des postes vers les sauvegardes, svc-backup non restreint | F3: Sauvegardes planifiées, comptes rendus hebdomadaires, site de secours, deux tests documentés | G3: 4 | H3: 3 | I3: =IF(OR(G3="",H3=""),"",G3*H3) -> 12 | J3: Réduire (A05, A08) et restriction de FW-31 en régie. Décision DG. | K3: T09, T02, T03, P01, P15, P17 · C02, C05, C11
A4: R03 | B4: Altération ou divulgation de données patients via l'application métier non corrigée | C4: APP01, DB01 | D4: Attaquant ayant pris pied en DMZ ou sur le VPN d'administration | E4: Correctif critique manquant (T05), hôte en retard de 74 jours (T06), aucun SLA, flux WEB01 vers APP01, RDP FW-17 | F4: Absence d'exposition directe à Internet, cloisonnement DMZ et VLAN 20 | G4: 4 | H4: 2 | I4: =IF(OR(G4="",H4=""),"",G4*H4) -> 8 | J4: Réduire (A09). Exception signée et mesures compensatoires si le correctif est reporté. | K4: T05, T06, T02, P05 · C03, C06, C09
A5: R04 | B5: Divulgation de données internes depuis les partages de fichiers après compromission d'un poste, y compris des données de santé si les partages en contiennent (hypothèse) | C5: SRV-FICHIERS, AD01 | D5: Hameçonnage (5 tentatives en 12 mois, P06) | E5: SMB ouvert à tout le VLAN 40 (FW-19), signature non obligatoire, retard de correctifs de 43 jours | F5: Blocage préventif de comptes, règles d'habilitation (P11) | G5: 3 | H5: 3 | I5: =IF(OR(G5="",H5=""),"",G5*H5) -> 9 | J5: Réduire partiellement (A09, A03). Segmentation complète A10 différée, risque résiduel accepté par la DG pour 12 mois. | K5: T02, T05, T06, P06 · C07
A6: R05 | B6: Interception ou dégradation des sessions du portail public | C6: WEB01, MEDI-PORTAL | D6: Attaquant réseau opportuniste | E6: TLS 1.0 signalé, port 80 ouvert, redirection non vérifiée | F6: Publication limitée à 443 et 80 par FW-01 et FW-08, reverse proxy en DMZ | G6: 2 | H6: 2 | I6: =IF(OR(G6="",H6=""),"",G6*H6) -> 4 | J6: Réduire à faible coût dans A09. À défaut, acceptation temporaire par la DSI. | K6: T02, T05 · C08
A7: R06 | B7: Indisponibilité ou altération de service causée par un changement mal maîtrisé | C7: MEDI-PORTAL, infrastructure | D7: Erreur interne lors des changements mensuels et trimestriels | E7: Conception et réalisation non standardisées (P13, P14), règle provisoire non retirée (FW-17) | F7: Revues de conception des projets majeurs, comptes rendus d'installation | G7: 3 | H7: 3 | I7: =IF(OR(G7="",H7=""),"",G7*H7) -> 9 | J7: Accepter temporairement (A04 différée en année 2) avec revue de changement renforcée en régie. Risque résiduel porté par la DO. | K7: P06, P08, P13, P14, T02 · C06
A8: R07 | I8: =IF(OR(G8="",H8=""),"",G8*H8)
A9: R08 | I9: =IF(OR(G9="",H9=""),"",G9*H9)
A10: R09 | I10: =IF(OR(G10="",H10=""),"",G10*H10)
A11: R10 | I11: =IF(OR(G11="",H11=""),"",G11*H11)

Sheet 05_PLAN_ACTION
A1: ID | B1: Mesure | C1: Source | D1: Coût € | E1: Pilote | F1: Échéance et livrable | G1: Retenir 1 / différer 0 | H1: Justification / risque
A2: A01 | B2: Risques : registre / méthode | C2: P16 | D2: 18000 | E2: RSSI | F2: T+4 mois : méthode, registre consolidé approuvé par la DG, revue trimestrielle, tableau de bord stratégique semestriel | G2: 1 | H2: Gérer les risques au niveau 1 (P10). Base de tous les arbitrages R01 à R06. Porte aussi l'étape stratégie (comptes rendus écrits).
A3: A02 | B3: Supervision : règles et reporting | C3: P16 | D3: 16000 | E3: RSSI et exploitation | F3: T+3 mois : procédure de traitement des alertes, plan de contrôle, reporting mensuel | G3: 1 | H3: Superviser au niveau 1 (P12). AL-1048 fermée sans ticket (C04, C10). R01.
A4: A03 | B4: PSSI / sensibilisation | C4: P16 | D4: 14000 | E4: RSSI et RH | F4: T+6 mois : PSSI révisée avec SLA de correctifs, PV de revue, campagne anti-hameçonnage | G4: 1 | H4: 5 hameçonnages sur 10 événements (P06), revue PSSI sans PV (P17), aucun SLA (C09). R04.
A5: A04 | B5: Standardisation conception / réalisation | C5: P16 | D5: 24000 | E5: DSI | F5: Différée en année 2 | G5: 0 | H5: Conception et réalisation déjà au niveau 2. Fiche SSI obligatoire préparée en régie. Risque résiduel R06.
A6: A05 | B6: Restauration et gestion incident | C6: P16 / T10 (même lot) | D6: 22000 | E6: Resp. infrastructures | F6: T+6 mois : PV de restauration pour 9 services sur 9, RTO et RPO mesurés, procédure d'incident | G6: 1 | H6: 2 tests sur 9 (T09), RTO de 8 h (P01). R02. Même lot que T10 restauration, compté une seule fois.
A7: A06 | B7: Outillage quantitatif | C7: P16 | D7: 35000 | E7: RSSI | F7: Différée en année 2 | G7: 0 | H7: La mesure quantitative relève du niveau 4, prématurée avec des processus à 1 ou 2. Alternative à A11, non cumulée. Risque résiduel : pilotage sans indicateurs chiffrés.
A8: A07 | B8: Conduite du changement | C8: P16 | D8: 14000 | E8: DG et RH | F8: Différée en année 2 | G8: 0 | H8: Utile mais moins urgente que R01 et R02. Risque résiduel : adhésion insuffisante aux nouvelles pratiques, suivie par la DG et les managers.
A9: A08 | B9: MFA renforcé / privilèges | C9: T10 | D9: 28000 | E9: DSI (IAM) | F9: T+3 mois : 100 % des comptes privilégiés sous MFA ou exception approuvée, revue des privilèges, svc-backup restreint | G9: 1 | H9: C01, C04, C11. R01 et R02. Déclaration de la DSI contredite par T04.
A10: A09 | B10: Programme vulnérabilités / patch | C10: T10 | D10: 18000 | E10: Resp. infrastructures | F10: APP01 sous 15 jours, puis T+4 mois : inventaire authentifié, SLA par criticité, TLS 1.0 retiré, signature SMB | G10: 1 | H10: C03, C07, C08, C09. R03, R04 et R05.
A11: A10 | B11: Segmentation réseau | C11: T10 | D11: 30000 | E11: DSI réseau | F11: Différée en année 2, FW-31 et FW-17 restreintes en régie sous un mois | G11: 0 | H11: Plafond atteint. Risque résiduel R04 et part de R02 acceptés par la DG pour 12 mois.
A12: A11 | B12: SIEM / détection / workflow | C12: T10 | D12: 35000 | E12: RSSI | F12: Différée en année 2 | G12: 0 | H12: Recoupe A02 pour le workflow d'alerte. Outil à choisir après stabilisation au niveau 2. Alternative à A06. Risque résiduel : détection limitée sur R01, compensée en partie par A02.
B15: Plafond | C15: 120000
B16: Engagement total | C16: =SUMPRODUCT(D2:D12,G2:G12) -> 116000
B17: Marge | C17: =C15-C16 -> 4000
B18: Statut | C18: =IF(C16<=C15,"BUDGET RESPECTÉ","DÉPASSEMENT") -> BUDGET RESPECTÉ
B20: Attention : A05 et le lot T10 restauration à 22 000 € désignent la même prestation et ne doivent pas être ajoutés deux fois.

Sheet 06_BAREME
A1: Bloc | B1: Évaluation | C1: Points max | D1: Points obtenus | E1: Commentaire
A2: G1 | B2: Périmètre | C2: 1.5
A3: G2 | B3: Niveau adéquat | C3: 2.5
A4: G3 | B4: 7 processus | C4: 3
A5: G4 | B5: Risques, plan, budget | C5: 3
A6: T1 | B6: Architecture / segmentation | C6: 2
A7: T2 | B7: IAM / MFA | C7: 2
A8: T3 | B8: Vulnérabilités | C8: 2
A9: T4 | B9: Logs et sauvegardes | C9: 2
A10: T5 | B10: Corrélation et conclusions | C10: 2
B13: Total gouvernance | C13: =SUM(D2:D5) -> 0
B14: Total technique | C14: =SUM(D6:D10) -> 0
B15: NOTE / 20 | C15: =SUM(C13:C14) -> 0
A17: Vérification des maxima | B17: Gouvernance 10 | C17: Technique 10 | D17: Total 20
